dagster_looker/__init__.py
dagster_looker/py.typed
dagster_looker/version.py
dagster_looker/api/__init__.py
dagster_looker/api/assets.py
dagster_looker/api/dagster_looker_api_translator.py
dagster_looker/api/resource.py
dagster_looker/api/components/__init__.py
dagster_looker/api/components/looker_component.py
dagster_looker/api/components/translation.py
dagster_looker/lkml/__init__.py
dagster_looker/lkml/asset_specs.py
dagster_looker/lkml/asset_utils.py
dagster_looker/lkml/dagster_looker_lkml_translator.py
dagster_looker/lkml/liquid_utils.py
dagster_looker/lkml/sqlglot_utils.py
dagster_looker-0.28.13.dist-info/licenses/LICENSE
dagster_looker-0.28.13.dist-info/METADATA
dagster_looker-0.28.13.dist-info/WHEEL
dagster_looker-0.28.13.dist-info/top_level.txt
dagster_looker-0.28.13.dist-info/RECORD
